appraise/__init__.py
appraise/input_fasta_prep.py
appraise/pymol_quantify_peptide_binding.py
appraise/score_calculation.py
appraise/utilities.py
appraise-1.2.4.dist-info/LICENSE
appraise-1.2.4.dist-info/METADATA
appraise-1.2.4.dist-info/WHEEL
appraise-1.2.4.dist-info/top_level.txt
appraise-1.2.4.dist-info/RECORD
