Metadata-Version: 2.1
Name: appraise
Version: 1.2.4
Summary: Scripts and functions needed for for APPARISE.
Author: Xiaozhe Ding
Author-email: xding@caltech.edu
Classifier: Programming Language :: Python :: 3
Classifier: Operating System :: MacOS :: MacOS X
Classifier: Operating System :: POSIX
License-File: LICENSE
Requires-Dist: scipy (>=1.4.1)
Requires-Dist: numpy (>=1.18.2)
Requires-Dist: pandas (>=1.1.5)
Requires-Dist: matplotlib (>=3.2.1)
Requires-Dist: seaborn (>=0.11.2)
